setup.py
highlighter/__init__.py
highlighter/templatetags/__init__.py
highlighter/templatetags/highlight_tags.py
twentytab_highlighter.egg-info/PKG-INFO
twentytab_highlighter.egg-info/SOURCES.txt
twentytab_highlighter.egg-info/dependency_links.txt
twentytab_highlighter.egg-info/top_level.txt