Metadata-Version: 1.0
Name: twentytab-highlighter
Version: 0.1
Summary: A django app permits to highlight the searched words (self.query) in a long text and truncates it, counts number of chars == max_length
Home-page: https://github.com/20tab/twentytab-highlighter
Author: 20Tab S.r.l.
Author-email: info@20tab.com
License: UNKNOWN
Platform: UNKNOWN
